{
  "m_GameObject": {
    "m_FileID": 0,
    "m_PathID": 0
  },
  "m_Enabled": 1,
  "m_Script": {
    "m_FileID": 0,
    "m_PathID": -4420957637576057513
  },
  "m_Name": "act24side_note_hub",
  "_sprites": [
    {
      "name": "note7",
      "guid": "ace939273cf7c084cb9d32f85cccbe33",
      "atlas": 0,
      "rect": {
        "x": 0,
        "y": 0,
        "w": 1020,
        "h": 510
      },
      "rotate": 0
    },
    {
      "name": "note6",
      "guid": "0e723b9fce67d454cb2df99425780a07",
      "atlas": 0,
      "rect": {
        "x": 0,
        "y": 512,
        "w": 1020,
        "h": 510
      },
      "rotate": 0
    },
    {
      "name": "note5",
      "guid": "5c5dd8303b207e845870ad6d2dd80730",
      "atlas": 1,
      "rect": {
        "x": 0,
        "y": 0,
        "w": 1020,
        "h": 510
      },
      "rotate": 0
    },
    {
      "name": "note4",
      "guid": "55a3322b55902994487aca45af91fc28",
      "atlas": 1,
      "rect": {
        "x": 0,
        "y": 512,
        "w": 1020,
        "h": 510
      },
      "rotate": 0
    },
    {
      "name": "note3",
      "guid": "339da3588ef5ff741b4aa70daac1a7e1",
      "atlas": 2,
      "rect": {
        "x": 0,
        "y": 0,
        "w": 1020,
        "h": 510
      },
      "rotate": 0
    },
    {
      "name": "note2",
      "guid": "41cd285e2b6594048ae530e9bd430b40",
      "atlas": 2,
      "rect": {
        "x": 0,
        "y": 512,
        "w": 1020,
        "h": 510
      },
      "rotate": 0
    },
    {
      "name": "note1",
      "guid": "9ba70060d77e0f14e9293bca278c3474",
      "atlas": 3,
      "rect": {
        "x": 0,
        "y": 0,
        "w": 1020,
        "h": 510
      },
      "rotate": 0
    },
    {
      "name": "right_arrow",
      "guid": "75144171df397fe4f96f6c03a5ff5aa7",
      "atlas": 3,
      "rect": {
        "x": 0,
        "y": 512,
        "w": 30,
        "h": 74
      },
      "rotate": 0
    },
    {
      "name": "left_arrow",
      "guid": "57b979184843b714781db8cef08a27e2",
      "atlas": 3,
      "rect": {
        "x": 0,
        "y": 588,
        "w": 30,
        "h": 74
      },
      "rotate": 0
    },
    {
      "name": "sprite_white",
      "guid": "d8768fc8ffc0bcd4ebfc727c34b92633",
      "atlas": 3,
      "rect": {
        "x": 0,
        "y": 664,
        "w": 32,
        "h": 32
      },
      "rotate": 0
    },
    {
      "name": "close",
      "guid": "bf7dcd42a8ba79f458979bba9c0eab4b",
      "atlas": 3,
      "rect": {
        "x": 0,
        "y": 698,
        "w": 32,
        "h": 32
      },
      "rotate": 0
    }
  ],
  "_atlases": [
    {
      "index": 0,
      "texture": {
        "m_FileID": 0,
        "m_PathID": -4099076455169034972
      },
      "alpha": {
        "m_FileID": 0,
        "m_PathID": 152523886130216291
      },
      "size": 1024
    },
    {
      "index": 1,
      "texture": {
        "m_FileID": 0,
        "m_PathID": -8220750185043844488
      },
      "alpha": {
        "m_FileID": 0,
        "m_PathID": -7457380095486708998
      },
      "size": 1024
    },
    {
      "index": 2,
      "texture": {
        "m_FileID": 0,
        "m_PathID": 6407008182388189441
      },
      "alpha": {
        "m_FileID": 0,
        "m_PathID": -244227933684949572
      },
      "size": 1024
    },
    {
      "index": 3,
      "texture": {
        "m_FileID": 0,
        "m_PathID": -3417550055239242126
      },
      "alpha": {
        "m_FileID": 0,
        "m_PathID": 4691980805909355366
      },
      "size": 1024
    }
  ],
  "_workDir": "",
  "_alphaSplit": 1,
  "_maxSize": 2,
  "_sign": {
    "m_sprites": [
      {
        "name": "note7",
        "guid": "ace939273cf7c084cb9d32f85cccbe33",
        "md5": "82ecbadd1f7740f3de779df445398af2"
      },
      {
        "name": "note6",
        "guid": "0e723b9fce67d454cb2df99425780a07",
        "md5": "2e8ce5ca83940bc7e960f161335f2ad8"
      },
      {
        "name": "note5",
        "guid": "5c5dd8303b207e845870ad6d2dd80730",
        "md5": "90e1b6c521b9fe8b370d7e4ebe5977b8"
      },
      {
        "name": "note4",
        "guid": "55a3322b55902994487aca45af91fc28",
        "md5": "afbb6ea54171b8424d6156de77c5a499"
      },
      {
        "name": "note3",
        "guid": "339da3588ef5ff741b4aa70daac1a7e1",
        "md5": "7e408553771627c0dcf7e82c2170a8fb"
      },
      {
        "name": "note2",
        "guid": "41cd285e2b6594048ae530e9bd430b40",
        "md5": "205aa1d6d9c3ddef101c5c78017e73c3"
      },
      {
        "name": "note1",
        "guid": "9ba70060d77e0f14e9293bca278c3474",
        "md5": "e6ab1359f1f60a7663f71024712887ed"
      },
      {
        "name": "right_arrow",
        "guid": "75144171df397fe4f96f6c03a5ff5aa7",
        "md5": "51d44548c887436df19580ee58080729"
      },
      {
        "name": "left_arrow",
        "guid": "57b979184843b714781db8cef08a27e2",
        "md5": "4d583d617926186f5c8a04d23e4bb0c3"
      },
      {
        "name": "sprite_white",
        "guid": "d8768fc8ffc0bcd4ebfc727c34b92633",
        "md5": "2ce5bb41cb46836bf4109504a7582745"
      },
      {
        "name": "close",
        "guid": "bf7dcd42a8ba79f458979bba9c0eab4b",
        "md5": "180a4b8902038f7d66c88bf98c982b29"
      }
    ],
    "m_atlases": [
      {
        "name": "act24side_note_hub#0",
        "guid": "c1b6e203f5975bb418d1274fc5e250f6",
        "md5": "47c6194f4fcd7e01982fe3e4f3ee4fa1"
      },
      {
        "name": "act24side_note_hub#1",
        "guid": "c49da98a6ccce6b42941f13f30f006a3",
        "md5": "d65a30f326503f7a2a70ce4f62280c0a"
      },
      {
        "name": "act24side_note_hub#2",
        "guid": "6c21c285351b6c34abc613151ee3a9a6",
        "md5": "39c1372589420885a4112019f7c3177a"
      },
      {
        "name": "act24side_note_hub#3",
        "guid": "6e4669e2d6b11054aa84980a4df67e71",
        "md5": "da5c4b595e54f2d1c958378b294c6cb2"
      }
    ],
    "m_alphas": [
      {
        "name": "act24side_note_hub#0a",
        "guid": "2630c2a2ea8164f48959843790454f63",
        "md5": "7848ff896549de236f0ce27ec70de1e6"
      },
      {
        "name": "act24side_note_hub#1a",
        "guid": "d2e1aba184a682143acf40d408c586dc",
        "md5": "02f3dc0803896e7ff077765acc516a3e"
      },
      {
        "name": "act24side_note_hub#2a",
        "guid": "b96513bdfdf8174458b0269ae692097a",
        "md5": "32fc6903242edec1fe85fd9398d76030"
      },
      {
        "name": "act24side_note_hub#3a",
        "guid": "7a7d700fbb19b11478017ffb47059d55",
        "md5": "a5ba0c0eda0e53d9fbe41766c61172f1"
      }
    ]
  }
}